keras_webhook_callback
