Metadata-Version: 2.1
Name: keras-webhook-callback
Version: 0.2.2
Summary: Receive notifications about your model training on your messaging app!
Home-page: https://github.com/AlexBella365/keras_webhook_callback
Author: Alex Bella
Author-email: alexbella365@gmail.com
License: GNU General Public License v3 (GPLv3)
Keywords: api python keras training callback
Platform: UNKNOWN
Classifier: Development Status :: 4 - Beta
Classifier: Intended Audience :: Developers
Classifier: License :: OSI Approved :: GNU General Public License v3 (GPLv3)
Classifier: Programming Language :: Python :: 3
Requires-Python: >=3.6
